mrbob/__init__.py
mrbob/bobexceptions.py
mrbob/cli.py
mrbob/configurator.py
mrbob/hooks.py
mrbob/parsing.py
mrbob/rendering.py
mrbob/template_sample/.mrbob.ini
mrbob/template_sample/sample.txt.bob
mrbob/template_starter/.mrbob.ini
mrbob/template_starter/sample.txt.bob
mrbob/tests/__init__.py
mrbob/tests/example.ini
mrbob/tests/example2.ini
mrbob/tests/example3.ini
mrbob/tests/example4.ini
mrbob/tests/example5.ini
mrbob/tests/example6.ini
mrbob/tests/ignored.ini
mrbob/tests/ignored_dirs.ini
mrbob/tests/question_order.ini
mrbob/tests/test_cli.py
mrbob/tests/test_configurator.py
mrbob/tests/test_hooks.py
mrbob/tests/test_parsing.py
mrbob/tests/test_rendering.py
mrbob/tests/unbound.ini
mrbob/tests/templates/strict_undefined.bob
mrbob/tests/templates/ask_hooks/.mrbob.ini
mrbob/tests/templates/ds_store/.DS_Store
mrbob/tests/templates/ds_store/.mrbob.ini
mrbob/tests/templates/empty/.mrbob.ini
mrbob/tests/templates/empty2/.mrbob.ini
mrbob/tests/templates/encodingč/mapča/ća.bob
mrbob/tests/templates/ignored/.mrbob.ini
mrbob/tests/templates/ignored/ignored
mrbob/tests/templates/ignored/ignored.txt
mrbob/tests/templates/ignored/not_ignored
mrbob/tests/templates/ignored_dirs/.mrbob.ini
mrbob/tests/templates/ignored_dirs/ignored/ignored_subdir/.gitignore
mrbob/tests/templates/ignored_dirs/ignored_stuff/stuff
mrbob/tests/templates/ignored_dirs/not_ignored/.gitignore
mrbob/tests/templates/missing_namespace_key/foo.bob
mrbob/tests/templates/missing_namespace_key/foo_jinja2.bob
mrbob/tests/templates/multiconfig/.mrbob.ini
mrbob/tests/templates/multiconfig/vars.bob
mrbob/tests/templates/questions1/.mrbob.ini
mrbob/tests/templates/questions2/.mrbob.ini
mrbob/tests/templates/questions3/.mrbob.ini
mrbob/tests/templates/questions4/.mrbob.ini
mrbob/tests/templates/questions5/.mrbob.ini
mrbob/tests/templates/renamed/+module+parts/+name+_etc/+name+.conf.bob
mrbob/tests/templates/renamedfile/foo.+name+.rst
mrbob/tests/templates/renamedir/parts+name+/part
mr.bob-1.0.1.dist-info/LICENSE
mr.bob-1.0.1.dist-info/METADATA
mr.bob-1.0.1.dist-info/WHEEL
mr.bob-1.0.1.dist-info/entry_points.txt
mr.bob-1.0.1.dist-info/top_level.txt
mr.bob-1.0.1.dist-info/RECORD
