Metadata-Version: 2.1
Name: mr.bob
Version: 1.0.1
Summary: Bob renders directory structure templates
Home-page: https://github.com/collective/mr.bob.git
Author: Domen Kozar, Tom Lazar
Author-email: 
License: BSD
Keywords: template skeleton
Classifier: Development Status :: 5 - Production/Stable
Classifier: Programming Language :: Python
Classifier: Programming Language :: Python :: Implementation :: CPython
Classifier: Programming Language :: Python :: Implementation :: PyPy
Classifier: Programming Language :: Python :: 3
Classifier: Programming Language :: Python :: 3.7
Classifier: Programming Language :: Python :: 3.8
Classifier: Programming Language :: Python :: 3.9
Classifier: Programming Language :: Python :: 3.10
Classifier: Programming Language :: Python :: 3.11
Classifier: Programming Language :: Python :: 3.12
Requires-Python: >=3.7
License-File: LICENSE
Requires-Dist: setuptools
Requires-Dist: six
Requires-Dist: Jinja2
Provides-Extra: development
Requires-Dist: zest.releaser ; extra == 'development'
Requires-Dist: Sphinx ; extra == 'development'
Provides-Extra: test
Requires-Dist: nose2 ; extra == 'test'
Requires-Dist: coverage ; extra == 'test'
Requires-Dist: flake8 ; extra == 'test'
